menu_generator/__init__.py
menu_generator/apps.py
menu_generator/defaults.py
menu_generator/menu.py
menu_generator/utils.py
menu_generator/validators.py
menu_generator/.mypy_cache/.gitignore
menu_generator/.mypy_cache/3.9/@plugins_snapshot.json
menu_generator/.mypy_cache/3.9/_ast.data.json
menu_generator/.mypy_cache/3.9/_ast.meta.json
menu_generator/.mypy_cache/3.9/_importlib_modulespec.data.json
menu_generator/.mypy_cache/3.9/_importlib_modulespec.meta.json
menu_generator/.mypy_cache/3.9/abc.data.json
menu_generator/.mypy_cache/3.9/abc.meta.json
menu_generator/.mypy_cache/3.9/array.data.json
menu_generator/.mypy_cache/3.9/array.meta.json
menu_generator/.mypy_cache/3.9/ast.data.json
menu_generator/.mypy_cache/3.9/ast.meta.json
menu_generator/.mypy_cache/3.9/builtins.data.json
menu_generator/.mypy_cache/3.9/builtins.meta.json
menu_generator/.mypy_cache/3.9/codecs.data.json
menu_generator/.mypy_cache/3.9/codecs.meta.json
menu_generator/.mypy_cache/3.9/genericpath.data.json
menu_generator/.mypy_cache/3.9/genericpath.meta.json
menu_generator/.mypy_cache/3.9/io.data.json
menu_generator/.mypy_cache/3.9/io.meta.json
menu_generator/.mypy_cache/3.9/mmap.data.json
menu_generator/.mypy_cache/3.9/mmap.meta.json
menu_generator/.mypy_cache/3.9/posix.data.json
menu_generator/.mypy_cache/3.9/posix.meta.json
menu_generator/.mypy_cache/3.9/sys.data.json
menu_generator/.mypy_cache/3.9/sys.meta.json
menu_generator/.mypy_cache/3.9/types.data.json
menu_generator/.mypy_cache/3.9/types.meta.json
menu_generator/.mypy_cache/3.9/typing.data.json
menu_generator/.mypy_cache/3.9/typing.meta.json
menu_generator/.mypy_cache/3.9/typing_extensions.data.json
menu_generator/.mypy_cache/3.9/typing_extensions.meta.json
menu_generator/.mypy_cache/3.9/_typeshed/__init__.data.json
menu_generator/.mypy_cache/3.9/_typeshed/__init__.meta.json
menu_generator/.mypy_cache/3.9/collections/__init__.data.json
menu_generator/.mypy_cache/3.9/collections/__init__.meta.json
django_menu_generator_ng-1.2.1.dist-info/AUTHORS.md
django_menu_generator_ng-1.2.1.dist-info/LICENSE
django_menu_generator_ng-1.2.1.dist-info/METADATA
django_menu_generator_ng-1.2.1.dist-info/WHEEL
django_menu_generator_ng-1.2.1.dist-info/top_level.txt
django_menu_generator_ng-1.2.1.dist-info/RECORD
